AUTHORS.rst
CONTRIBUTING.rst
HISTORY.rst
MANIFEST.in
README.rst
setup.cfg
setup.py
csxnexus/__init__.py
csxnexus/cli.py
csxnexus/csxnexus.py
csxnexus.egg-info/PKG-INFO
csxnexus.egg-info/SOURCES.txt
csxnexus.egg-info/dependency_links.txt
csxnexus.egg-info/entry_points.txt
csxnexus.egg-info/not-zip-safe
csxnexus.egg-info/requires.txt
csxnexus.egg-info/top_level.txt
docs/Makefile
docs/authors.rst
docs/conf.py
docs/contributing.rst
docs/history.rst
docs/index.rst
docs/installation.rst
docs/make.bat
docs/readme.rst
docs/usage.rst
tests/__init__.py
tests/test_csxnexus.py