Metadata-Version: 1.1
Name: csxnexus
Version: 0.1.0
Summary: Python Boilerplate contains all the boilerplate you need to create a Python package.
Home-page: https://github.com/pyrabbit/csxnexus
Author: Matthew Orahood
Author-email: morahood@gmail.com
License: UNKNOWN
Keywords: csxnexus
Platform: UNKNOWN
Classifier: Development Status :: 2 - Pre-Alpha
Classifier: Intended Audience :: Developers
Classifier: Natural Language :: English
Classifier: Programming Language :: Python :: 2
Classifier: Programming Language :: Python :: 2.7
Classifier: Programming Language :: Python :: 3
Classifier: Programming Language :: Python :: 3.4
Classifier: Programming Language :: Python :: 3.5
Classifier: Programming Language :: Python :: 3.6
